languagecodes/__init__.py
languagecodes/generate.py
languagecodes/iso-639-3.tab
languagecodes/iso639.py
languagecodes/py.typed
languagecodes/synonyms.py
languagecodes/util.py
languagecodes-1.1.1.dist-info/LICENSE
languagecodes-1.1.1.dist-info/METADATA
languagecodes-1.1.1.dist-info/WHEEL
languagecodes-1.1.1.dist-info/namespace_packages.txt
languagecodes-1.1.1.dist-info/top_level.txt
languagecodes-1.1.1.dist-info/RECORD
