Metadata-Version: 2.1
Name: languagecodes
Version: 1.1.1
Summary: A library that normalises language codes
Home-page: http://github.com/alephdata/languagecodes
Author: Friedrich Lindenberg
Author-email: friedrich@pudo.org
License: MIT
Keywords: names languages iso
Platform: UNKNOWN
Classifier: Development Status :: 3 - Alpha
Classifier: Intended Audience :: Developers
Classifier: License :: OSI Approved :: MIT License
Classifier: Operating System :: OS Independent
Classifier: Programming Language :: Python :: 3.3
Classifier: Programming Language :: Python :: 3.4
Classifier: Programming Language :: Python :: 3.5
Classifier: Programming Language :: Python :: 3.6
Requires-Dist: banal (<2.0.0,>=1.0.0)
Provides-Extra: dev
Requires-Dist: wheel (>=0.29.0) ; extra == 'dev'
Requires-Dist: twine ; extra == 'dev'
Requires-Dist: mypy ; extra == 'dev'
Requires-Dist: flake8 (>=2.6.0) ; extra == 'dev'
Requires-Dist: nose ; extra == 'dev'
Requires-Dist: coverage (>=4.1) ; extra == 'dev'
